polidoro_argument/__init__.py
polidoro_argument/action.py
polidoro_argument/argument.py
polidoro_argument/command.py
polidoro_argument/help_action.py
polidoro_argument/help_formatter.py
polidoro_argument/params.py
polidoro_argument/polidoro_argument_parser.py
tests/__init__.py
tests/generate_test_files.py
tests/helper.py
tests/manual_test.py
tests/test_polidoro_argument_parser.py
polidoro_argument-4.1.0.dist-info/LICENSE
polidoro_argument-4.1.0.dist-info/METADATA
polidoro_argument-4.1.0.dist-info/WHEEL
polidoro_argument-4.1.0.dist-info/top_level.txt
polidoro_argument-4.1.0.dist-info/RECORD
