Metadata-Version: 2.1
Name: polidoro-argument
Version: 4.1.0
Summary: Package to create command line arguments for Python.
Home-page: https://github.com/heitorpolidoro/polidoro-argument
Author: Heitor Polidoro
License: unlicense
Platform: UNKNOWN
Classifier: Programming Language :: Python :: 3.8
Classifier: License :: OSI Approved :: MIT License
Classifier: Operating System :: OS Independent
License-File: LICENSE
